pdfsquash.py
pdfsquash-0.0.3.dist-info/LICENSE
pdfsquash-0.0.3.dist-info/METADATA
pdfsquash-0.0.3.dist-info/WHEEL
pdfsquash-0.0.3.dist-info/entry_points.txt
pdfsquash-0.0.3.dist-info/top_level.txt
pdfsquash-0.0.3.dist-info/zip-safe
pdfsquash-0.0.3.dist-info/RECORD
