Metadata-Version: 2.1
Name: pdfsquash
Version: 0.0.3
Summary: Tool(s) for placing multiple PDF pages on a sheet for printin
Home-page: https://github.com/pgmmpk/pdfsquash
Author: Mike Kroutikov
Author-email: pgmmpk@gmail.com
License: MIT
Keywords: pdf
Classifier: License :: OSI Approved :: MIT License
Classifier: Programming Language :: Python :: 3
License-File: LICENSE
Requires-Dist: pypdf2 (~=3.0.1)
